<?xml version="1.0" encoding="utf-8"?>
<CommonFlatConf>
  <floors>
    <PFloor>
      <id>33</id>
      <points>
        <PPoint>
          <id>131</id>
          <pos>
            <x>1087297322</x>
            <z>1067770819</z>
          </pos>
          <height>1077936128</height>
        </PPoint>
        <PPoint>
          <id>111</id>
          <pos>
            <x>1087297322</x>
            <z>-1066611726</z>
          </pos>
          <height>1077936128</height>
        </PPoint>
        <PPoint>
          <id>118</id>
          <pos>
            <x>-1084957547</x>
            <z>-1066611726</z>
          </pos>
          <height>1077936128</height>
        </PPoint>
        <PPoint>
          <id>130</id>
          <pos>
            <x>-1084957547</x>
            <z>1067770819</z>
          </pos>
          <height>1077936128</height>
        </PPoint>
      </points>
      <walls>
        <PWall>
          <id>245</id>
          <pointStart>131</pointStart>
          <pointEnd>111</pointEnd>
          <width>1036831949</width>
          <height>1077936128</height>
          <splinePoint></splinePoint>
          <startShift>
            <x>0</x>
            <z>0</z>
          </startShift>
          <endShift>
            <x>0</x>
            <z>0</z>
          </endShift>
          <windows>
            <PWindow>
              <id>300</id>
              <lotid>31</lotid>
              <width>1072064102</width>
              <height>1069547520</height>
              <startPointDist>1054951342</startPointDist>
              <over_floor>1058642330</over_floor>
            </PWindow>
          </windows>
          <colors>
            <PSurface>
              <containerID>wall3d_245_p2</containerID>
              <lot>
                <id>74339</id>
              </lot>
              <matMod>
                <colorsets>
                  <PColorSet>
                    <color>
                      <r>1065353216</r>
                      <g>1065353216</g>
                      <b>1065353216</b>
                      <a>1065353216</a>
                    </color>
                  </PColorSet>
                </colorsets>
                <texScale>
                  <x>1072792170</x>
                  <y>1078460416</y>
                </texScale>
                <texOffset>
                  <x>0</x>
                  <y>0</y>
                </texOffset>
                <mapingRotate>0</mapingRotate>
              </matMod>
            </PSurface>
            <PSurface>
              <containerID>wall3d_245_p1</containerID>
              <lot>
                <id>4954</id>
              </lot>
              <matMod>
                <colorsets>
                  <PColorSet>
                    <color>
                      <r>1064178811</r>
                      <g>1063172178</g>
                      <b>1062501089</b>
                      <a>1065353216</a>
                    </color>
                  </PColorSet>
                </colorsets>
                <texScale>
                  <x>1065353216</x>
                  <y>1065353216</y>
                </texScale>
                <mapingRotate>0</mapingRotate>
              </matMod>
            </PSurface>
          </colors>
        </PWall>
        <PWall>
          <id>287</id>
          <pointStart>118</pointStart>
          <pointEnd>130</pointEnd>
          <width>1036831949</width>
          <height>1077936128</height>
          <splinePoint></splinePoint>
          <startShift>
            <x>0</x>
            <z>0</z>
          </startShift>
          <endShift>
            <x>0</x>
            <z>0</z>
          </endShift>
          <colors>
            <PSurface>
              <containerID>wall3d_287_p2</containerID>
              <lot>
                <id>74339</id>
              </lot>
              <matMod>
                <colorsets>
                  <PColorSet>
                    <color>
                      <r>1065353216</r>
                      <g>1065353216</g>
                      <b>1065353216</b>
                      <a>1065353216</a>
                    </color>
                  </PColorSet>
                </colorsets>
                <texScale>
                  <x>1072792170</x>
                  <y>1078460416</y>
                </texScale>
                <texOffset>
                  <x>0</x>
                  <y>0</y>
                </texOffset>
                <mapingRotate>0</mapingRotate>
              </matMod>
            </PSurface>
            <PSurface>
              <containerID>wall3d_287_p1</containerID>
              <lot>
                <id>4954</id>
              </lot>
              <matMod>
                <colorsets>
                  <PColorSet>
                    <color>
                      <r>1064178811</r>
                      <g>1063172178</g>
                      <b>1062501089</b>
                      <a>1065353216</a>
                    </color>
                  </PColorSet>
                </colorsets>
                <texScale>
                  <x>1065353216</x>
                  <y>1065353216</y>
                </texScale>
                <mapingRotate>0</mapingRotate>
              </matMod>
            </PSurface>
          </colors>
        </PWall>
        <PWall>
          <id>294</id>
          <pointStart>130</pointStart>
          <pointEnd>131</pointEnd>
          <width>1036831949</width>
          <height>1077936128</height>
          <splinePoint></splinePoint>
          <startShift>
            <x>0</x>
            <z>0</z>
          </startShift>
          <endShift>
            <x>0</x>
            <z>0</z>
          </endShift>
          <windows>
            <PWindow>
              <id>299</id>
              <lotid>31</lotid>
              <width>1072064102</width>
              <height>1069547520</height>
              <startPointDist>1060320051</startPointDist>
              <over_floor>1058642330</over_floor>
            </PWindow>
          </windows>
          <doors>
            <PDoor>
              <id>286</id>
              <lotid>25364</lotid>
              <width>1063675494</width>
              <height>1073993482</height>
              <startPointDist>1045220557</startPointDist>
              <over_floor>0</over_floor>
              <doState>false</doState>
              <options>s_rehandle:13769</options>
            </PDoor>
          </doors>
          <colors>
            <PSurface>
              <containerID>wall3d_294_p2</containerID>
              <lot>
                <id>74339</id>
              </lot>
              <matMod>
                <colorsets>
                  <PColorSet>
                    <color>
                      <r>1065353216</r>
                      <g>1065353216</g>
                      <b>1065353216</b>
                      <a>1065353216</a>
                    </color>
                  </PColorSet>
                </colorsets>
                <texScale>
                  <x>1072792170</x>
                  <y>1078460416</y>
                </texScale>
                <texOffset>
                  <x>0</x>
                  <y>0</y>
                </texOffset>
                <mapingRotate>0</mapingRotate>
              </matMod>
            </PSurface>
            <PSurface>
              <containerID>wall3d_294_p1</containerID>
              <lot>
                <id>47681</id>
              </lot>
              <matMod>
                <colorsets>
                  <PColorSet>
                    <color>
                      <r>1065353216</r>
                      <g>1065353216</g>
                      <b>1065353216</b>
                      <a>1065353216</a>
                    </color>
                  </PColorSet>
                </colorsets>
                <texScale>
                  <x>1072792170</x>
                  <y>1070071808</y>
                </texScale>
                <texOffset>
                  <x>0</x>
                  <y>0</y>
                </texOffset>
                <mapingRotate>4194304</mapingRotate>
              </matMod>
            </PSurface>
          </colors>
        </PWall>
        <PWall>
          <id>298</id>
          <pointStart>111</pointStart>
          <pointEnd>118</pointEnd>
          <width>1036831949</width>
          <height>1077936128</height>
          <splinePoint></splinePoint>
          <startShift>
            <x>0</x>
            <z>0</z>
          </startShift>
          <endShift>
            <x>0</x>
            <z>0</z>
          </endShift>
          <windows>
            <PWindow>
              <id>301</id>
              <lotid>31</lotid>
              <width>1072064102</width>
              <height>1069547520</height>
              <startPointDist>1049247089</startPointDist>
              <over_floor>1058642330</over_floor>
            </PWindow>
          </windows>
          <colors>
            <PSurface>
              <containerID>wall3d_298_p2</containerID>
              <lot>
                <id>74339</id>
              </lot>
              <matMod>
                <colorsets>
                  <PColorSet>
                    <color>
                      <r>1065353216</r>
                      <g>1065353216</g>
                      <b>1065353216</b>
                      <a>1065353216</a>
                    </color>
                  </PColorSet>
                </colorsets>
                <texScale>
                  <x>1072792170</x>
                  <y>1078460416</y>
                </texScale>
                <texOffset>
                  <x>0</x>
                  <y>0</y>
                </texOffset>
                <mapingRotate>0</mapingRotate>
              </matMod>
            </PSurface>
            <PSurface>
              <containerID>wall3d_298_p1</containerID>
              <lot>
                <id>4954</id>
              </lot>
              <matMod>
                <colorsets>
                  <PColorSet>
                    <color>
                      <r>1064178811</r>
                      <g>1063172178</g>
                      <b>1062501089</b>
                      <a>1065353216</a>
                    </color>
                  </PColorSet>
                </colorsets>
                <texScale>
                  <x>1065353216</x>
                  <y>1065353216</y>
                </texScale>
                <mapingRotate>0</mapingRotate>
              </matMod>
            </PSurface>
          </colors>
        </PWall>
      </walls>
      <furn>
        <PFurniture>
          <id>302</id>
          <lotid>70408</lotid>
          <pos>
            <x>1077829208</x>
            <y>-1514144256</y>
            <z>-1079209841</z>
          </pos>
          <overFloor>-1514144256</overFloor>
          <rot>
            <x>0</x>
            <y>0</y>
            <z>0</z>
          </rot>
          <size>
            <x>1073750213</x>
            <y>1062215877</y>
            <z>1063356727</z>
          </size>
          <colors/>
        </PFurniture>
      </furn>
      <rooms>
        <PRoom>
          <id>278</id>
          <name>Room</name>
          <roomSType>living room</roomSType>
          <pointid>
            <int>131</int>
            <int>111</int>
            <int>118</int>
            <int>130</int>
          </pointid>
          <plinthLot>
            <id></id>
          </plinthLot>
          <colors>
            <PSurface>
              <containerID>floor</containerID>
              <lot>
                <id>51863</id>
              </lot>
              <matMod>
                <colorsets>
                  <PColorSet>
                    <color>
                      <r>1065353216</r>
                      <g>1065353216</g>
                      <b>1065353216</b>
                      <a>1065353216</a>
                    </color>
                  </PColorSet>
                </colorsets>
                <texScale>
                  <x>1065353216</x>
                  <y>1065353216</y>
                </texScale>
                <texOffset>
                  <x>0</x>
                  <y>0</y>
                </texOffset>
                <mapingRotate>0</mapingRotate>
              </matMod>
            </PSurface>
            <PSurface>
              <containerID>ceil</containerID>
              <lot>
                <id>47643</id>
              </lot>
              <matMod>
                <colorsets>
                  <PColorSet>
                    <color>
                      <r>1065353216</r>
                      <g>1065353216</g>
                      <b>1065353216</b>
                      <a>1065353216</a>
                    </color>
                  </PColorSet>
                </colorsets>
                <texScale>
                  <x>1072792170</x>
                  <y>1070071808</y>
                </texScale>
                <texOffset>
                  <x>0</x>
                  <y>0</y>
                </texOffset>
                <mapingRotate>4194304</mapingRotate>
              </matMod>
            </PSurface>
          </colors>
        </PRoom>
      </rooms>
      <height>1077936128</height>
      <startWalkPosition></startWalkPosition>
      <startWalkRotation></startWalkRotation>
      <name>Этаж 1</name>
    </PFloor>
  </floors>
  <settings>
    <projName>2K_58m2</projName>
    <autosave>true</autosave>
    <asTimeInterval>1114636288</asTimeInterval>
    <showHints>true</showHints>
    <lastSaveTime>1499434303</lastSaveTime>
  </settings>
  <editedFloorid>9</editedFloorid>
  <sunRotation></sunRotation>
  <version>1.1</version>
  <PNorthDir>0</PNorthDir>
  <sunIntensity>1028443341</sunIntensity>
  <camHeightinWalk>0</camHeightinWalk>
  <projectState>1</projectState>
  <camera2DPosition>
    <y>1091865515</y>
    <z>856829496</z>
  </camera2DPosition>
  <camera2DZoom>1082130432</camera2DZoom>
</CommonFlatConf>
